eida_statistics_aggregator/__init__.py
eida_statistics_aggregator/aggregator.py
eida_statistics_aggregator/eida_statistic.py
eida_statistics_aggregator/stat_collection.py
eida_statistics_aggregator-0.8.1.dist-info/entry_points.txt
eida_statistics_aggregator-0.8.1.dist-info/licenses/LICENSE
eida_statistics_aggregator-0.8.1.dist-info/WHEEL
eida_statistics_aggregator-0.8.1.dist-info/METADATA
eida_statistics_aggregator-0.8.1.dist-info/RECORD
