Metadata-Version: 2.4
Name: eida-statistics-aggregator
Version: 0.8.1
Summary: Aggregates and anonymize data distribution logs from seiscomp, ready to be sent to the central EIDA KPI service.
Requires-Python: >=3.11
License-File: LICENSE
Requires-Dist: click>=8.3.1
Requires-Dist: fdsnnetextender>=5.0.2
Requires-Dist: mmh3>=5.2.0
Requires-Dist: python-hll2>=2.0.1
Requires-Dist: python-magic>=0.4.27
Requires-Dist: requests>=2.32.5
